README.md
setup.py
cli/__init__.py
cli/app.c
cli/app.pyx
cli/ext/Makefile
cli/ext/add.c
cli/ext/add.h
dalongrong_cythoncli.egg-info/PKG-INFO
dalongrong_cythoncli.egg-info/SOURCES.txt
dalongrong_cythoncli.egg-info/dependency_links.txt
dalongrong_cythoncli.egg-info/entry_points.txt
dalongrong_cythoncli.egg-info/not-zip-safe
dalongrong_cythoncli.egg-info/requires.txt
dalongrong_cythoncli.egg-info/top_level.txt