Metadata-Version: 2.1
Name: dalongrong-cythoncli
Version: 0.0.18
Summary: a simple cli project
Home-page: UNKNOWN
Author: dalongrong
Author-email: 1141591465@qq.com
License: UNKNOWN
Project-URL: Documentation, https://github.com/rongfengliang/cython-c-pip-demo.git
Project-URL: Say Thanks!, https://github.com/rongfengliang/cython-c-pip-demo.git
Project-URL: Source, https://github.com/rongfengliang/cython-c-pip-demo.git
Project-URL: Tracker, https://github.com/rongfengliang/cython-c-pip-demo.git
Platform: UNKNOWN
Classifier: Programming Language :: Python :: 3
Classifier: License :: OSI Approved :: MIT License
Classifier: Operating System :: OS Independent
